copy2android/M2A.py
copy2android/__init__.py
copy2android-1.1.5.dist-info/LICENCE.txt
copy2android-1.1.5.dist-info/METADATA
copy2android-1.1.5.dist-info/WHEEL
copy2android-1.1.5.dist-info/top_level.txt
copy2android-1.1.5.dist-info/RECORD
