Metadata-Version: 2.1
Name: copy2android
Version: 1.1.5
Summary: Copy From Mac,Paste On Android
Home-page: https://github.com/loyal888/copy2android
Author: loyal888
Author-email: h916232476@gmail.com
License: UNKNOWN
Platform: UNKNOWN
Classifier: Programming Language :: Python :: 3
Classifier: License :: OSI Approved :: MIT License
Classifier: Operating System :: OS Independent
License-File: LICENCE.txt
